save_load_vars/LICENSE
save_load_vars/README.MD
save_load_vars/__init__.py
save_load_vars/requirements.txt
save_load_vars/thirdparty.json
save_load_vars-0.11.dist-info/LICENSE.rst
save_load_vars-0.11.dist-info/METADATA
save_load_vars-0.11.dist-info/WHEEL
save_load_vars-0.11.dist-info/top_level.txt
save_load_vars-0.11.dist-info/RECORD
